menglingtool_redis/__init__.py
menglingtool_redis/redis_tool.py
menglingtool_redis-1.0.1.dist-info/METADATA
menglingtool_redis-1.0.1.dist-info/WHEEL
menglingtool_redis-1.0.1.dist-info/top_level.txt
menglingtool_redis-1.0.1.dist-info/RECORD
